case_insensitive_user/__init__.py
case_insensitive_user/admin.py
case_insensitive_user/apps.py
case_insensitive_user/conf.py
case_insensitive_user/models.py
case_insensitive_user/migrations/0001_initial.py
case_insensitive_user/migrations/__init__.py
tests/__init__.py
tests/test_models.py
django_case_insensitive_user-0.2.2.dist-info/LICENSE
django_case_insensitive_user-0.2.2.dist-info/METADATA
django_case_insensitive_user-0.2.2.dist-info/WHEEL
django_case_insensitive_user-0.2.2.dist-info/top_level.txt
django_case_insensitive_user-0.2.2.dist-info/RECORD
